{"stats":{"minecraft:killed":{"born_in_chaos_v1:zombie_clown":3,"minecraft:witch":1,"born_in_chaos_v1:restless_spirit":1,"born_in_chaos_v1:zombie_lumberjack":1,"minecraft:spider":16,"born_in_chaos_v1:siamese_skeletonsright":1,"minecraft:skeleton":30,"alexsmobs:leafcutter_ant":2,"minecraft:chicken":15,"born_in_chaos_v1:skeleton_thrasher":2,"minecraft:tropical_fish":1,"alexsmobs:kangaroo":7,"minecraft:pig":35,"alexsmobs:anteater":1,"minecraft:salmon":1,"minecraft:creeper":5,"minecraft:sheep":22,"minecraft:pillager":2,"minecraft:zombie":40,"born_in_chaos_v1:dread_hound":4,"born_in_chaos_v1:corpse_fly":15,"born_in_chaos_v1:door_knight":2,"born_in_chaos_v1:siamese_skeletonsleft":1,"minecraft:cow":8,"alexsmobs:raccoon":2,"born_in_chaos_v1:zombie_bruiser":1,"born_in_chaos_v1:maggot":9,"born_in_chaos_v1:baby_spider":3,"alexsmobs:bison":2,"minecraft:drowned":2,"born_in_chaos_v1:swarmer":1,"born_in_chaos_v1:mother_spider":1,"minecraft:squid":2,"born_in_chaos_v1:decrepit_skeleton":4,"alexsmobs:emu":6,"alexsmobs:cockroach":1,"alexsmobs:gazelle":1,"alexsmobs:crow":2,"minecraft:villager":1,"minecraft:enderman":2},"minecraft:dropped":{"minecraft:birch_planks":10,"minecraft:cooked_beef":1,"minecraft:baked_potato":15,"minecraft:glow_ink_sac":3,"botania:red_mystical_flower":2,"minecraft:lantern":1,"born_in_chaos_v1:dark_ritual_dagger":1,"minecraft:flint":1,"born_in_chaos_v1:phantom_powder":2,"minecraft:cornflower":4,"minecraft:jungle_sapling":2,"alexsmobs:emu_feather":4,"minecraft:iron_pickaxe":3,"botania:white_mystical_flower":2,"minecraft:white_wool":2,"minecraft:bone":1,"minecraft:gravel":21,"minecraft:cherry_boat":1,"minecraft:sugar_cane":8,"minecraft:cooked_chicken":1,"alexsmobs:animal_dictionary":1,"minecraft:obsidian":2,"minecraft:rotten_flesh":11,"minecraft:oak_planks":9,"minecraft:azure_bluet":3,"minecraft:carrot":23,"minecraft:arrow":7,"botania:red_double_flower":1,"botania:brown_double_flower":1,"minecraft:oak_slab":16,"minecraft:black_dye":1,"born_in_chaos_v1:shattered_skull":1,"minecraft:wheat_seeds":16,"minecraft:oak_fence":2,"minecraft:iron_helmet":1,"minecraft:cobblestone":58,"botania:light_gray_double_flower":1,"minecraft:granite":1,"minecraft:tropical_fish":3,"minecraft:coal":11,"minecraft:stick":6,"minecraft:oxeye_daisy":6,"minecraft:gray_wool":1,"minecraft:ink_sac":3,"minecraft:wooden_axe":1,"minecraft:cherry_planks":1,"minecraft:iron_leggings":2,"minecraft:string":2,"minecraft:pink_petals":30,"minecraft:redstone":28,"minecraft:smooth_basalt":5,"minecraft:dandelion":38,"minecraft:furnace":1,"botania:purple_mushroom":1,"minecraft:stone_sword":1,"minecraft:iron_boots":2,"minecraft:big_dripleaf":5,"minecraft:hay_block":14,"create:veridium":12,"botania:cyan_mystical_flower":1,"alexsmobs:cockroach_wing_fragment":2,"minecraft:iron_chestplate":3,"minecraft:andesite":4,"slashblade:slashblade":1,"minecraft:oak_sapling":4,"minecraft:spider_eye":1,"minecraft:stone_pickaxe":1,"minecraft:wooden_pickaxe":1,"minecraft:raw_gold":1,"minecraft:black_wool":1},"minecraft:broken":{"minecraft:iron_shovel":1,"minecraft:iron_boots":1,"minecraft:stone_axe":1,"minecraft:iron_sword":1,"minecraft:stone_sword":1,"slashblade:slashblade":3,"minecraft:shield":3,"minecraft:iron_pickaxe":3,"minecraft:iron_helmet":2},"minecraft:custom":{"minecraft:animals_bred":1,"minecraft:interact_with_crafting_table":125,"minecraft:open_barrel":5,"minecraft:bell_ring":5,"minecraft:leave_game":26,"minecraft:time_since_death":46868,"minecraft:sprint_one_cm":2942152,"minecraft:damage_blocked_by_shield":9595,"minecraft:drop":115,"minecraft:talked_to_villager":8,"minecraft:play_time":841250,"minecraft:deaths":25,"minecraft:jump":16669,"minecraft:walk_on_water_one_cm":151995,"minecraft:enchant_item":1,"minecraft:interact_with_furnace":267,"minecraft:interact_with_loom":4,"minecraft:sleep_in_bed":10,"minecraft:damage_dealt":43102,"minecraft:player_kills":2,"minecraft:crouch_one_cm":57711,"minecraft:interact_with_anvil":2,"minecraft:mob_kills":268,"minecraft:sword_summoned":111,"minecraft:damage_dealt_resisted":3958,"minecraft:climb_one_cm":5005,"minecraft:walk_one_cm":1552076,"minecraft:damage_dealt_absorbed":80,"minecraft:sneak_time":17694,"minecraft:walk_under_water_one_cm":59251,"minecraft:boat_one_cm":136404,"minecraft:interact_with_blast_furnace":7,"minecraft:total_world_time":841250,"minecraft:time_since_rest":46913,"minecraft:damage_taken":20198,"minecraft:damage_absorbed":30,"minecraft:swim_one_cm":178167,"minecraft:fly_one_cm":3749443,"minecraft:open_chest":29,"minecraft:fall_one_cm":531181},"minecraft:used":{"minecraft:moss_block":18,"minecraft:iron_shovel":386,"minecraft:chest":3,"minecraft:shield":125,"minecraft:iron_sword":610,"minecraft:rotten_flesh":25,"minecraft:iron_chestplate":1,"minecraft:carrot":151,"minecraft:axolotl_bucket":14,"minecraft:obsidian":2,"minecraft:big_dripleaf":19,"minecraft:glass":72,"minecraft:jungle_sapling":1,"born_in_chaos_v1:corpse_maggot":2,"minecraft:lava_bucket":12,"minecraft:furnace":19,"minecraft:oak_planks":31,"minecraft:stone_pickaxe":61,"minecraft:wooden_pickaxe":33,"minecraft:composter":2,"minecraft:clay":23,"minecraft:golden_apple":1,"minecraft:glow_berries":64,"alexscaves:cave_book":1,"minecraft:blast_furnace":1,"minecraft:bread":71,"create:asurine":3,"minecraft:gravel":66,"minecraft:andesite":14,"minecraft:oak_boat":1,"minecraft:bone_meal":54,"minecraft:azalea":3,"minecraft:cherry_boat":6,"born_in_chaos_v1:dark_ritual_dagger":2,"minecraft:stone_sword":161,"minecraft:enchanting_table":1,"minecraft:flint_and_steel":2,"create:veridium":54,"slashblade:bladestand_1":1,"minecraft:cooked_chicken":13,"born_in_chaos_v1:fried_maggot":4,"minecraft:orange_bed":2,"minecraft:torch":491,"minecraft:dirt":212,"minecraft:anvil":2,"alexsmobs:cooked_kangaroo_meat":8,"minecraft:granite":4,"minecraft:iron_hoe":114,"minecraft:iron_axe":144,"slashblade:slashblade":990,"minecraft:cherry_trapdoor":4,"minecraft:minecart":4,"minecraft:cooked_beef":25,"minecraft:powder_snow_bucket":2,"minecraft:calcite":18,"minecraft:cobbled_deepslate":163,"minecraft:cooked_mutton":27,"minecraft:water_bucket":69,"minecraft:birch_planks":27,"minecraft:baked_potato":24,"minecraft:cherry_planks":2,"minecraft:fletching_table":1,"minecraft:rail":87,"minecraft:crafting_table":29,"minecraft:white_bed":4,"minecraft:diamond_pickaxe":658,"minecraft:oxeye_daisy":2,"minecraft:iron_pickaxe":966,"minecraft:stone_axe":88,"minecraft:cobblestone":226,"minecraft:cooked_porkchop":62,"minecraft:bucket":98,"alexsmobs:animal_dictionary":53},"minecraft:killed_by":{"born_in_chaos_v1:nightmare_stalker":1,"minecraft:creeper":6,"born_in_chaos_v1:baby_spider":2,"alexsmobs:emu":1,"minecraft:zombie":3,"born_in_chaos_v1:skeleton_thrasher":1,"minecraft:enderman":1,"alexsmobs:bison":1,"minecraft:skeleton":4,"alexsmobs:kangaroo":1,"born_in_chaos_v1:dread_hound":1,"born_in_chaos_v1:maggot":1},"minecraft:crafted":{"minecraft:black_dye":2,"minecraft:smooth_stone":8,"minecraft:oak_planks":220,"minecraft:cooked_chicken":13,"minecraft:cherry_boat":1,"minecraft:stone":9,"minecraft:cooked_mutton":27,"minecraft:glass":88,"minecraft:diamond_leggings":1,"minecraft:iron_boots":2,"minecraft:chest":7,"minecraft:oak_slab":30,"minecraft:cooked_porkchop":62,"minecraft:crafting_table":24,"slashblade:slashblade":3,"minecraft:iron_helmet":2,"minecraft:wooden_pickaxe":1,"minecraft:baked_potato":24,"slashblade:bladestand_1":1,"minecraft:fletching_table":2,"minecraft:birch_planks":124,"slashblade:proudsoul_ingot":1,"minecraft:iron_chestplate":2,"minecraft:diamond_pickaxe":1,"minecraft:charcoal":15,"minecraft:shield":3,"minecraft:stick":156,"minecraft:iron_ingot":182,"minecraft:iron_pickaxe":4,"minecraft:iron_block":6,"minecraft:stone_sword":1,"minecraft:gold_ingot":11,"minecraft:composter":2,"slashblade:proudsoul":1,"minecraft:cherry_planks":36,"minecraft:wooden_sword":2,"slashblade:proudsoul_sphere":1,"minecraft:iron_nugget":9,"slashblade:proudsoul_crystal":1,"minecraft:furnace":11,"minecraft:blast_furnace":1,"minecraft:bone_meal":54,"minecraft:flint_and_steel":1,"minecraft:cherry_trapdoor":4,"minecraft:iron_axe":1,"born_in_chaos_v1:fried_maggot":4,"minecraft:iron_hoe":1,"minecraft:stone_pickaxe":1,"minecraft:minecart":1,"minecraft:wheat":182,"minecraft:cooked_beef":28,"minecraft:enchanting_table":1,"alexsmobs:cooked_kangaroo_meat":8,"minecraft:iron_sword":2,"minecraft:bucket":1,"minecraft:stone_axe":1,"minecraft:bread":66,"minecraft:air":0,"minecraft:oak_boat":1,"minecraft:iron_shovel":2,"minecraft:iron_leggings":2,"minecraft:anvil":2,"minecraft:white_bed":4,"minecraft:torch":488,"minecraft:clay":23,"minecraft:diamond_chestplate":1,"slashblade:proudsoul_tiny":8},"minecraft:picked_up":{"minecraft:wooden_axe":1,"minecraft:iron_chestplate":2,"minecraft:wheat":16,"botania:black_double_flower":3,"botania:light_blue_mushroom":1,"minecraft:string":15,"minecraft:iron_leggings":1,"botania:light_gray_double_flower":2,"minecraft:cherry_boat":7,"alexsmobs:emu_feather":8,"minecraft:cobbled_deepslate":254,"minecraft:bucket":1,"minecraft:calcite":18,"minecraft:azalea":9,"minecraft:iron_pickaxe":3,"born_in_chaos_v1:stimulating_decoction":2,"minecraft:iron_boots":1,"minecraft:furnace":11,"minecraft:stick":8,"born_in_chaos_v1:shattered_skull":3,"minecraft:big_dripleaf":26,"minecraft:oak_fence":4,"born_in_chaos_v1:phantom_powder":4,"minecraft:torch":43,"born_in_chaos_v1:pileof_dark_metal":1,"minecraft:porkchop":62,"minecraft:cherry_log":9,"botania:white_mystical_flower":6,"minecraft:orange_bed":2,"minecraft:stone_sword":3,"slashblade:proudsoul":4,"minecraft:rotten_flesh":55,"botania:light_gray_mystical_flower":1,"minecraft:tropical_fish":6,"create:asurine":53,"create:veridium":66,"botania:blue_double_flower":1,"minecraft:obsidian":29,"minecraft:cobblestone":420,"minecraft:birch_log":42,"minecraft:pink_petals":31,"minecraft:feather":22,"minecraft:cooked_beef":1,"minecraft:andesite":18,"minecraft:jungle_log":2,"alexsmobs:bison_fur":3,"minecraft:flint":8,"minecraft:tuff":13,"create:raw_zinc":59,"alexscaves:sundrop":1,"minecraft:lapis_lazuli":23,"minecraft:dirt":326,"minecraft:lantern":1,"born_in_chaos_v1:monster_skin":3,"minecraft:bone":57,"botania:cyan_mystical_flower":5,"minecraft:bow":1,"minecraft:stonecutter":1,"minecraft:wheat_seeds":51,"minecraft:raw_gold":54,"botania:purple_mystical_flower":2,"botania:gray_mushroom":2,"minecraft:fletching_table":1,"slashblade:slashblade":1,"minecraft:bamboo":23,"minecraft:powered_rail":4,"minecraft:moss_block":31,"botania:gray_mystical_flower":4,"minecraft:oak_planks":10,"botania:red_mystical_flower":3,"botania:gray_double_flower":1,"minecraft:sand":100,"sophisticatedbackpacks:iron_backpack":1,"minecraft:ink_sac":5,"minecraft:grass_block":1,"alexsmobs:animal_dictionary":3,"alexsmobs:kangaroo_hide":9,"minecraft:sugar":3,"minecraft:diamond":25,"botania:orange_mushroom":1,"minecraft:granite":7,"minecraft:emerald":9,"minecraft:oak_sapling":4,"minecraft:crafting_table":5,"minecraft:azure_bluet":6,"botania:brown_double_flower":2,"minecraft:chicken":15,"botania:white_mushroom":1,"minecraft:clay_ball":128,"minecraft:leather_leggings":1,"minecraft:wooden_pickaxe":4,"minecraft:shield":1,"minecraft:cornflower":4,"minecraft:moss_carpet":12,"minecraft:iron_axe":1,"born_in_chaos_v1:intoxicating_decoction":1,"botania:magenta_mystical_flower":3,"minecraft:beef":28,"minecraft:oak_boat":1,"born_in_chaos_v1:gnawed_bones":1,"minecraft:jungle_sapling":3,"minecraft:light_gray_wool":1,"minecraft:minecart":4,"minecraft:sugar_cane":54,"minecraft:egg":1,"minecraft:raw_iron":190,"botania:purple_mushroom":3,"botania:green_mushroom":1,"born_in_chaos_v1:pieceofdarkmetal":14,"minecraft:carrot":146,"minecraft:redstone":107,"minecraft:arrow":26,"botania:lime_mystical_flower":2,"minecraft:hay_block":38,"botania:blue_mystical_flower":5,"born_in_chaos_v1:dark_ritual_dagger":1,"botania:green_mystical_flower":2,"minecraft:glow_berries":43,"minecraft:mutton":32,"minecraft:rail":153,"alexsmobs:kangaroo_meat":8,"minecraft:white_wool":21,"minecraft:oxeye_daisy":8,"born_in_chaos_v1:fused_bone":2,"minecraft:stripped_oak_log":1,"born_in_chaos_v1:corpse_maggot":18,"born_in_chaos_v1:monster_flesh":3,"minecraft:glow_ink_sac":3,"minecraft:leather":5,"minecraft:birch_planks":21,"minecraft:oak_log":167,"minecraft:gunpowder":5,"botania:black_mystical_flower":2,"alexsmobs:cockroach_wing_fragment":3,"minecraft:iron_ingot":28,"minecraft:stone_pickaxe":1,"minecraft:cooked_chicken":1,"minecraft:flowering_azalea":5,"minecraft:book":6,"minecraft:oak_slab":16,"botania:purple_double_flower":1,"minecraft:smooth_basalt":5,"born_in_chaos_v1:ethereal_spirit":1,"minecraft:dandelion":38,"minecraft:gravel":87,"minecraft:amethyst_shard":4,"minecraft:spider_eye":5,"botania:red_double_flower":1,"minecraft:slime_ball":1,"minecraft:stone_axe":2,"minecraft:iron_helmet":1,"minecraft:cherry_sapling":2,"minecraft:gray_wool":1,"minecraft:baked_potato":15,"minecraft:black_wool":1,"botania:brown_mystical_flower":2,"minecraft:coal":291,"minecraft:ender_pearl":1},"minecraft:mined":{"botania:red_mystical_flower":1,"minecraft:cherry_log":9,"minecraft:jungle_leaves":2,"minecraft:obsidian":29,"minecraft:cave_vines_plant":1,"minecraft:granite":4,"botania:light_blue_mushroom":1,"minecraft:grass_block":220,"botania:black_double_flower":2,"botania:light_gray_mystical_flower":2,"alexscaves:sundrop":1,"minecraft:tall_seagrass":1,"botania:purple_mystical_flower":2,"minecraft:iron_ore":117,"minecraft:cobbled_deepslate":2,"minecraft:fire":1,"minecraft:moss_carpet":2,"minecraft:deepslate_lapis_ore":1,"minecraft:fletching_table":1,"create:asurine":54,"botania:green_mushroom":1,"minecraft:sculk_shrieker":2,"minecraft:cave_vines":9,"minecraft:dirt_path":1,"botania:brown_mystical_flower":1,"minecraft:azalea":9,"create:veridium":61,"minecraft:orange_bed":2,"botania:green_mystical_flower":1,"minecraft:deepslate_redstone_ore":8,"minecraft:clay":32,"minecraft:torch":12,"minecraft:calcite":15,"minecraft:poppy":1,"botania:purple_double_flower":1,"minecraft:glass":4,"minecraft:cobblestone":2,"botania:blue_mystical_flower":4,"minecraft:oak_planks":3,"minecraft:sugar_cane":28,"botania:light_gray_double_flower":1,"botania:black_mystical_flower":1,"minecraft:wall_torch":3,"minecraft:pink_petals":7,"minecraft:powered_rail":4,"minecraft:birch_log":36,"minecraft:wheat":1,"minecraft:grass":314,"botania:gray_mushroom":1,"minecraft:oak_log":77,"botania:gray_double_flower":1,"minecraft:sand":100,"minecraft:dirt":82,"minecraft:smooth_basalt":7,"minecraft:stonecutter":1,"minecraft:oak_leaves":15,"minecraft:deepslate":333,"create:zinc_ore":32,"minecraft:tuff":34,"minecraft:dark_oak_leaves":4,"minecraft:deepslate_diamond_ore":26,"gravestone:gravestone":21,"botania:brown_double_flower":1,"botania:orange_mushroom":1,"minecraft:moss_block":14,"minecraft:hay_block":24,"botania:purple_mushroom":1,"botania:magenta_mystical_flower":1,"minecraft:redstone_ore":4,"minecraft:furnace":10,"minecraft:carrots":44,"botania:white_mushroom":1,"minecraft:andesite":16,"minecraft:big_dripleaf_stem":3,"minecraft:bookshelf":2,"minecraft:deepslate_iron_ore":64,"minecraft:rail":153,"minecraft:lantern":1,"minecraft:stripped_oak_log":1,"minecraft:bamboo":3,"minecraft:stone":447,"botania:lime_mystical_flower":2,"minecraft:flowering_azalea":5,"botania:lime_mushroom":1,"minecraft:dandelion":1,"minecraft:oak_fence":1,"minecraft:crafting_table":6,"minecraft:emerald_ore":5,"minecraft:sculk_sensor":1,"minecraft:copper_ore":1,"minecraft:tall_grass":58,"minecraft:lapis_ore":1,"minecraft:deepslate_gold_ore":44,"minecraft:sculk":2,"minecraft:diorite":2,"minecraft:big_dripleaf":1,"botania:cyan_mystical_flower":2,"minecraft:birch_planks":2,"minecraft:birch_leaves":8,"botania:white_mystical_flower":2,"minecraft:coal_ore":187,"minecraft:cherry_leaves":4,"minecraft:gravel":71,"botania:gray_mystical_flower":4,"minecraft:gold_ore":9}},"DataVersion":3465}